FlowViewFt/FlowViewFt.py
FlowViewFt/__init__.py
FlowViewFt/core/FlowViewFtMiddleware.py
FlowViewFt/core/FlowViewFtParams.py
FlowViewFt/core/FlowViewFtState.py
FlowViewFt/core/FlowViewFtView.py
FlowViewFt/core/__init__.py
FlowViewFt/view/InternalErrorView.py
FlowViewFt/view/NotFoundView.py
FlowViewFt/view/__init__.py
example/contador/src/main.py
example/contador/src/state/counter_state.py
example/contador/src/view/counter_view.py
example/contador/src/view/home_view.py
flowviewft-0.1.3.dist-info/licenses/LICENSE
flowviewft-0.1.3.dist-info/METADATA
flowviewft-0.1.3.dist-info/WHEEL
flowviewft-0.1.3.dist-info/top_level.txt
flowviewft-0.1.3.dist-info/RECORD
